evfl/__init__.py
evfl/_version.py
evfl/actor.py
evfl/common.py
evfl/container.py
evfl/dic.py
evfl/entry_point.py
evfl/enums.py
evfl/event.py
evfl/evfl.py
evfl/flowchart.py
evfl/repr_util.py
evfl/timeline.py
evfl/util.py
evfl-1.2.0.dist-info/LICENSE
evfl-1.2.0.dist-info/METADATA
evfl-1.2.0.dist-info/WHEEL
evfl-1.2.0.dist-info/top_level.txt
evfl-1.2.0.dist-info/RECORD
