Metadata-Version: 2.1
Name: evfl
Version: 1.2.0
Summary: Library for parsing and writing Breath of the Wild Event Flow files
Home-page: https://github.com/leoetlino/evfl
Author: leoetlino
Author-email: leo@leolam.fr
Classifier: License :: OSI Approved :: GNU General Public License v2 or later (GPLv2+)
Classifier: Topic :: Software Development :: Libraries
Classifier: Operating System :: OS Independent
Classifier: Programming Language :: Python :: 3 :: Only
Requires-Python: >=3.6
License-File: LICENSE
